ltfatpy/__init__.py
ltfatpy/version.py
ltfatpy/comp/__init__.py
ltfatpy/comp/arg_firwin.py
ltfatpy/comp/assert_groworder.py
ltfatpy/comp/assert_sigreshape_post.py
ltfatpy/comp/assert_sigreshape_pre.py
ltfatpy/comp/comp_hermite.py
ltfatpy/comp/comp_hermite_all.py
ltfatpy/comp/comp_sigreshape_post.py
ltfatpy/comp/comp_sigreshape_pre.py
ltfatpy/comp/comp_window.py
ltfatpy/comp/gabpars_from_windowsignal.py
ltfatpy/fourier/__init__.py
ltfatpy/fourier/dcti.py
ltfatpy/fourier/dctii.py
ltfatpy/fourier/dctiii.py
ltfatpy/fourier/dctiv.py
ltfatpy/fourier/dft.py
ltfatpy/fourier/dsti.py
ltfatpy/fourier/dstii.py
ltfatpy/fourier/dstiii.py
ltfatpy/fourier/dstiv.py
ltfatpy/fourier/fftindex.py
ltfatpy/fourier/fftreal.py
ltfatpy/fourier/fftresample.py
ltfatpy/fourier/idft.py
ltfatpy/fourier/ifftreal.py
ltfatpy/fourier/isevenfunction.py
ltfatpy/fourier/middlepad.py
ltfatpy/fourier/pderiv.py
ltfatpy/fourier/pgauss.py
ltfatpy/fourier/pherm.py
ltfatpy/fourier/psech.py
ltfatpy/gabor/__init__.py
ltfatpy/gabor/dgt.py
ltfatpy/gabor/dgtlength.py
ltfatpy/gabor/dgtreal.py
ltfatpy/gabor/gabdual.py
ltfatpy/gabor/gabframediag.py
ltfatpy/gabor/gabimagepars.py
ltfatpy/gabor/gabphasegrad.py
ltfatpy/gabor/gabtight.py
ltfatpy/gabor/gabwin.py
ltfatpy/gabor/idgt.py
ltfatpy/gabor/idgtreal.py
ltfatpy/gabor/instfreqplot.py
ltfatpy/gabor/phaselock.py
ltfatpy/gabor/phaseplot.py
ltfatpy/gabor/phaseunlock.py
ltfatpy/gabor/plotdgt.py
ltfatpy/gabor/plotdgtreal.py
ltfatpy/gabor/s0norm.py
ltfatpy/gabor/sgram.py
ltfatpy/gabor/tfplot.py
ltfatpy/signals/__init__.py
ltfatpy/signals/greasy.py
ltfatpy/signals/gspi.py
ltfatpy/signals/linus.py
ltfatpy/sigproc/__init__.py
ltfatpy/sigproc/fir2long.py
ltfatpy/sigproc/firkaiser.py
ltfatpy/sigproc/firwin.py
ltfatpy/sigproc/groupthresh.py
ltfatpy/sigproc/largestn.py
ltfatpy/sigproc/largestr.py
ltfatpy/sigproc/long2fir.py
ltfatpy/sigproc/normalize.py
ltfatpy/sigproc/rms.py
ltfatpy/sigproc/thresh.py
ltfatpy/tests/__init__.py
ltfatpy/tests/comp/__init__.py
ltfatpy-0.0.0.dist-info/licenses/AUTHORS.rst
ltfatpy-0.0.0.dist-info/licenses/LICENSE.rst
ltfatpy-0.0.0.dist-info/METADATA
ltfatpy-0.0.0.dist-info/WHEEL
ltfatpy-0.0.0.dist-info/top_level.txt
ltfatpy-0.0.0.dist-info/RECORD
