Metadata-Version: 2.4
Name: ltfatpy
Version: 0.0.0
Summary: The Large Time-Frequency Toolbox (LTFAT) in Python
Author: Florent Jaillet, Denis Arrivault
Author-email: Valentin Emiya <valentin.emiya@lis-lab.fr>
Project-URL: Sources, https://gitlab.lis-lab.fr/dev/ltfatpy
Project-URL: Documentation, https://dev.pages.lis-lab.fr/ltfatpy
Project-URL: Bug Tracker, https://gitlab.lis-lab.fr/dev/ltfatpy/-/issues
Classifier: Development Status :: 5 - Production/Stable
Classifier: Intended Audience :: Science/Research
Classifier: Intended Audience :: End Users/Desktop
Classifier: Intended Audience :: Developers
Classifier: Natural Language :: English
Classifier: Operating System :: MacOS :: MacOS X
Classifier: Operating System :: POSIX :: Linux
Classifier: Programming Language :: C
Classifier: Programming Language :: Python :: 3.4
Classifier: Programming Language :: Python :: 3.5
Classifier: Programming Language :: Python :: 3.6
Classifier: Programming Language :: Python :: 3.7
Classifier: Programming Language :: Python :: 3.8
Classifier: Programming Language :: Python :: 3.9
Classifier: Programming Language :: Python :: 3.10
Classifier: Programming Language :: Python :: 3.11
Classifier: Programming Language :: Python :: 3.12
Classifier: Topic :: Scientific/Engineering :: Mathematics
Classifier: Topic :: Scientific/Engineering
Requires-Python: >=3.4
License-File: LICENSE.rst
License-File: AUTHORS.rst
Requires-Dist: scipy>=0.18
Requires-Dist: importlib_resources
Requires-Dist: numpy>=1.8
Requires-Dist: matplotlib>=1.4
Provides-Extra: test
Requires-Dist: pytest; extra == "test"
Requires-Dist: nose; extra == "test"
Requires-Dist: coverage; extra == "test"
Provides-Extra: doc
Requires-Dist: sphinx==5.0; extra == "doc"
Requires-Dist: numpydoc; extra == "doc"
Requires-Dist: sphinx_gallery; extra == "doc"
Requires-Dist: matplotlib; extra == "doc"
Requires-Dist: sphinx_rtd_theme; extra == "doc"
Dynamic: license-file
